deepdata/__init__.py
deepdata/cli.py
deepdata/config.py
deepdata/core/__init__.py
deepdata/core/agent.py
deepdata/core/agent_context.py
deepdata/core/display.py
deepdata/core/event_bus.py
deepdata/core/event_sink.py
deepdata/core/message_handler.py
deepdata/core/message_utils.py
deepdata/core/registry.py
deepdata/core/session_registry.py
deepdata/core/streaming.py
deepdata/core/workspace_manager.py
deepdata/core/schema/session_data.sql
deepdata/core/schema/session_index.sql
deepdata/core/session/__init__.py
deepdata/core/session/export.py
deepdata/core/session/info.py
deepdata/core/session/queries.py
deepdata/core/session/store.py
deepdata/deep_plot/__init__.py
deepdata/deep_plot/agent.py
deepdata/deep_plot/tools.py
deepdata/mle/__init__.py
deepdata/mle/config.py
deepdata/mle/journal.py
deepdata/mle/node.py
deepdata/mle/orchestrator.py
deepdata/mle/storage.py
deepdata/mle/agents/__init__.py
deepdata/mle/agents/data_report.py
deepdata/mle/agents/debug.py
deepdata/mle/agents/draft.py
deepdata/mle/agents/improve.py
deepdata/mle/agents/shared.py
deepdata/mle/context/__init__.py
deepdata/mle/context/base.py
deepdata/mle/context/discovery.py
deepdata/mle/context/preset_loader.py
deepdata/mle/context/presets/mlebench.json
deepdata/mle/utils/__init__.py
deepdata/mle/utils/git.py
deepdata/plotly/__init__.py
deepdata/plotly/client.py
deepdata/plotly/mcp_tools.py
deepdata/plotly/tools.py
deepdata/plotly/server/__init__.py
deepdata/plotly/server/capture_config.py
deepdata/plotly/server/router.py
deepdata/plotly/server/templates.py
deepdata/plotly/server/services/__init__.py
deepdata/plotly/server/services/event_service.py
deepdata/plotly/server/services/headless_handler.py
deepdata/plotly/server/services/headless_subscriber.py
deepdata/plotly/server/services/plot_service.py
deepdata/plotly/server/services/screenshot_service.py
deepdata/plotly/server/templates/logs.html
deepdata/plotly/server/templates/plot.html
deepdata/utils/__init__.py
deepdata/utils/async_helpers.py
claude_deepdata-0.1.0.dist-info/METADATA
claude_deepdata-0.1.0.dist-info/WHEEL
claude_deepdata-0.1.0.dist-info/entry_points.txt
claude_deepdata-0.1.0.dist-info/RECORD
