Metadata-Version: 2.4
Name: claude-deepdata
Version: 0.1.0
Summary: An agent framework built on Claude SDK for data analysis, visualization, and ML automation
Project-URL: Homepage, https://github.com/YiyangLu/Deep-Data
Project-URL: Documentation, https://github.com/YiyangLu/Deep-Data#readme
Project-URL: Repository, https://github.com/YiyangLu/Deep-Data
Project-URL: Issues, https://github.com/YiyangLu/Deep-Data/issues
Author: Deep Data Team
License-Expression: MIT
Keywords: agent,claude,data-analysis,ml,plotly,visualization
Classifier: Development Status :: 4 - Beta
Classifier: Intended Audience :: Developers
Classifier: Intended Audience :: Science/Research
Classifier: License :: OSI Approved :: MIT License
Classifier: Programming Language :: Python :: 3
Classifier: Programming Language :: Python :: 3.10
Classifier: Programming Language :: Python :: 3.11
Classifier: Programming Language :: Python :: 3.12
Classifier: Topic :: Scientific/Engineering :: Artificial Intelligence
Classifier: Topic :: Scientific/Engineering :: Visualization
Requires-Python: >=3.10
Requires-Dist: claude-agent-sdk>=0.1.0
Requires-Dist: fastapi>=0.104.0
Requires-Dist: flask>=3.0.0
Requires-Dist: gitpython>=3.1.0
Requires-Dist: jinja2>=3.1.0
Requires-Dist: kaleido==0.2.1
Requires-Dist: pandas>=2.0.0
Requires-Dist: plotly<6.0.0,>=5.18.0
Requires-Dist: python-multipart>=0.0.6
Requires-Dist: requests>=2.28.0
Requires-Dist: rich>=13.0.0
Requires-Dist: uvicorn[standard]>=0.24.0
Requires-Dist: websockets>=12.0
Provides-Extra: dev
Requires-Dist: pytest-asyncio>=0.21.0; extra == 'dev'
Requires-Dist: pytest>=7.0.0; extra == 'dev'
Provides-Extra: ml
Requires-Dist: catboost>=1.2.0; extra == 'ml'
Requires-Dist: lightgbm>=4.0.0; extra == 'ml'
Requires-Dist: optuna>=3.4.0; extra == 'ml'
Requires-Dist: scikit-learn>=1.3.0; extra == 'ml'
Requires-Dist: xgboost>=2.0.0; extra == 'ml'
